qnavi/src/utils/__init__.py
qnavi/src/utils/colors.py
qnavi/src/utils/qnav.py
qnavi-0.0.3.dist-info/LICENSE
qnavi-0.0.3.dist-info/METADATA
qnavi-0.0.3.dist-info/WHEEL
qnavi-0.0.3.dist-info/top_level.txt
qnavi-0.0.3.dist-info/RECORD
