Metadata-Version: 2.1
Name: qnavi
Version: 0.0.3
Summary: A python package for quick access/navigating most of the used fuctions.
Author-email: Wuse Tech Author <wusetech001@gmail.com>
License: Copyright (c) 2018 The Python Packaging Authority        
Classifier: Programming Language :: Python :: 3
Classifier: License :: OSI Approved :: MIT License
Classifier: Operating System :: OS Independent
Requires-Python: >=3.7
License-File: LICENSE
